cesnet_datazoo/__init__.py
cesnet_datazoo/config.py
cesnet_datazoo/constants.py
cesnet_datazoo/datasets/__init__.py
cesnet_datazoo/datasets/cesnet_dataset.py
cesnet_datazoo/datasets/datasets.py
cesnet_datazoo/datasets/datasets_constants.py
cesnet_datazoo/datasets/loaders.py
cesnet_datazoo/datasets/statistics.py
cesnet_datazoo/datasets/metadata/__init__.py
cesnet_datazoo/datasets/metadata/dataset_metadata.py
cesnet_datazoo/datasets/metadata/metadata.csv
cesnet_datazoo/metrics/__init__.py
cesnet_datazoo/metrics/classification_report.py
cesnet_datazoo/metrics/provider_metrics.py
cesnet_datazoo/pytables_data/__init__.py
cesnet_datazoo/pytables_data/apps_split.py
cesnet_datazoo/pytables_data/data_scalers.py
cesnet_datazoo/pytables_data/indices_setup.py
cesnet_datazoo/pytables_data/pytables_dataset.py
cesnet_datazoo/utils/__init__.py
cesnet_datazoo/utils/class_info.py
cesnet_datazoo/utils/download.py
cesnet_datazoo/utils/fileutils.py
cesnet_datazoo/utils/random.py
cesnet_datazoo-0.1.15.dist-info/licenses/LICENCE
cesnet_datazoo-0.1.15.dist-info/METADATA
cesnet_datazoo-0.1.15.dist-info/WHEEL
cesnet_datazoo-0.1.15.dist-info/top_level.txt
cesnet_datazoo-0.1.15.dist-info/RECORD
