Metadata-Version: 2.4
Name: cesnet-datazoo
Version: 0.1.15
Summary: A toolkit for large network traffic datasets
Author-email: Jan Luxemburk <luxemburk@cesnet.cz>, Karel Hynek <hynekkar@cesnet.cz>
Maintainer-email: Jan Luxemburk <luxemburk@cesnet.cz>, Karel Hynek <hynekkar@cesnet.cz>
License-Expression: BSD-3-Clause
Project-URL: Homepage, https://github.com/CESNET/cesnet-datazoo
Project-URL: Documentation, https://cesnet.github.io/cesnet-datazoo/
Project-URL: Bug Tracker, https://github.com/CESNET/cesnet-datazoo/issues
Keywords: traffic classification,datasets,machine learning
Classifier: Programming Language :: Python :: 3.10
Classifier: Intended Audience :: Science/Research
Classifier: Operating System :: OS Independent
Requires-Python: >=3.10
License-File: LICENCE
Requires-Dist: cesnet_models
Requires-Dist: matplotlib
Requires-Dist: numpy
Requires-Dist: pandas
Requires-Dist: pydantic!=2.9.*,<2.12.0,>=2.0
Requires-Dist: PyYAML
Requires-Dist: requests
Requires-Dist: scikit-learn
Requires-Dist: seaborn
Requires-Dist: tables>=3.10.0
Requires-Dist: torch>=1.10
Requires-Dist: tqdm
Provides-Extra: dev
Requires-Dist: build; extra == "dev"
Requires-Dist: mkdocs-autorefs; extra == "dev"
Requires-Dist: mkdocs-material-extensions; extra == "dev"
Requires-Dist: mkdocs-material; extra == "dev"
Requires-Dist: mkdocs; extra == "dev"
Requires-Dist: mkdocstrings-python; extra == "dev"
Requires-Dist: mkdocstrings; extra == "dev"
Requires-Dist: twine; extra == "dev"
Dynamic: license-file
